duckql_django/__init__.py
duckql_django/models.py
duckql_django/schema.py
duckql_django/version.py
duckql_django/wrapper.py
duckql_django-0.9.0.dist-info/LICENSE
duckql_django-0.9.0.dist-info/METADATA
duckql_django-0.9.0.dist-info/WHEEL
duckql_django-0.9.0.dist-info/top_level.txt
duckql_django-0.9.0.dist-info/RECORD
