Metadata-Version: 2.1
Name: duckql-django
Version: 0.9.0
Summary: duckQL Django bindings
Home-page: https://github.com/Sibyx/duckql-django
Author: Jakub Dubec
Author-email: jakub.dubec@gmail.com
License: MIT
Classifier: Development Status :: 3 - Alpha
Classifier: Environment :: Console
Classifier: Programming Language :: Python
Classifier: Programming Language :: Python :: 3.9
Classifier: Programming Language :: Python :: 3.10
Classifier: Programming Language :: Python :: 3.11
Classifier: Programming Language :: Python :: Implementation :: PyPy
Classifier: Framework :: Django :: 2.0
Classifier: Framework :: Django :: 2.1
Classifier: Framework :: Django :: 2.2
Classifier: Framework :: Django :: 3.0
Classifier: Framework :: Django :: 3.1
Classifier: Framework :: Django :: 3.2
Classifier: Framework :: Django :: 4.0
Classifier: Intended Audience :: Developers
Classifier: License :: OSI Approved :: MIT License
Classifier: Topic :: Database
Classifier: Topic :: Software Development :: Libraries
License-File: LICENSE
Requires-Dist: django >=2
Requires-Dist: duckql >=0.9.1
Requires-Dist: django-enum-choices >=2.1.2
